TestTube/__init__.py
TestTube/serve.py
testtube_sc-1.1.0.dist-info/METADATA
testtube_sc-1.1.0.dist-info/WHEEL
testtube_sc-1.1.0.dist-info/top_level.txt
testtube_sc-1.1.0.dist-info/RECORD
