Metadata-Version: 2.4
Name: TestTube-sc
Version: 1.1.0
Summary: Websites built fast.
Home-page: https://github.com/spacecat031/TestTube
Author: SpaceCat
Author-email: unavailab@notarealemail.com
Classifier: Programming Language :: Python :: 3
Classifier: License :: OSI Approved :: MIT License
Classifier: Operating System :: OS Independent
Requires-Python: >=3.7
Dynamic: author
Dynamic: author-email
Dynamic: classifier
Dynamic: description
Dynamic: home-page
Dynamic: requires-python
Dynamic: summary
